{"dataset": "food_101_small", "label": "pizza", "close_positive": ["data/1001116.jpg", "data/1008104.jpg", "data/1026922.jpg", "data/103708.jpg", "data/105910.jpg", "data/1067986.jpg", "data/1083380.jpg", "data/1107714.jpg", "data/1123386.jpg", "data/1137400.jpg", "data/1180001.jpg", "data/1183595.jpg", "data/1202689.jpg", "data/121960.jpg", "data/1223284.jpg", "data/1228171.jpg", "data/12718.jpg", "data/1289139.jpg", "data/131561.jpg", "data/1325918.jpg", "data/1326065.jpg", "data/134462.jpg"], "hard_positive": ["data/1008844.jpg", "data/1032754.jpg", "data/1098197.jpg", "data/1106738.jpg", "data/1119571.jpg", "data/1157438.jpg", "data/1179703.jpg", "data/1207213.jpg", "data/1220156.jpg", "data/1243215.jpg", "data/1247645.jpg", "data/1248346.jpg", "data/1265335.jpg", "data/1275885.jpg", "data/1284978.jpg", "data/1287004.jpg", "data/1312761.jpg", "data/1327402.jpg"], "easy_negative": [], "hard_negative": ["data/1008144.jpg", "data/1035854.jpg", "data/1038357.jpg", "data/1065078.jpg", "data/1069629.jpg", "data/1105700.jpg", "data/1209973.jpg"], "semihard_negative": ["data/1187078.jpg", "data/1248053.jpg", "data/1131482.jpg", "data/109401.jpg", "data/1332030.jpg", "data/1073502.jpg", "data/1059612.jpg", "data/1234617.jpg", "data/1103265.jpg", "data/1120178.jpg", "data/1062556.jpg", "data/1019604.jpg", "data/104818.jpg", "data/1299349.jpg", "data/1356247.jpg", "data/1114358.jpg", "data/1021189.jpg", "data/1155748.jpg", "data/1044237.jpg", "data/1210873.jpg", "data/101156.jpg", "data/1275263.jpg", "data/1060159.jpg", "data/1018953.jpg", "data/1001332.jpg", "data/1050629.jpg", "data/1066205.jpg", "data/1286743.jpg", "data/1061807.jpg", "data/1103466.jpg"]}